examples/example_cnn.py
examples/example_input_space.py
examples/example_mlp.py
examples/example_mnist_mlp.py
jaxzoo/__init__.py
jaxzoo/base_model.py
jaxzoo/cnn.py
jaxzoo/mlp.py
jaxzoo/neural_components.py
jaxzoo/spaces.py
jaxzoo/utils.py
tests/test_spaces.py
jaxzoo-1.0.dist-info/LICENSE
jaxzoo-1.0.dist-info/METADATA
jaxzoo-1.0.dist-info/WHEEL
jaxzoo-1.0.dist-info/top_level.txt
jaxzoo-1.0.dist-info/RECORD
