Metadata-Version: 2.2
Name: jaxzoo
Version: 1.0
Summary: Highly flexible input/output space agnostic NN models in JAX.
Home-page: https://github.com/tboulet/JAX-Neural-Zoo
Author: Timothé Boulet
Author-email: timothe.boulet0@gmail.com
License: MIT
License-File: LICENSE
Dynamic: author
Dynamic: author-email
Dynamic: description
Dynamic: description-content-type
Dynamic: home-page
Dynamic: license
Dynamic: summary
